ddtrace_graphql_juaco/__init__.py
ddtrace_graphql_juaco/base.py
ddtrace_graphql_juaco/patch.py
ddtrace_graphql_juaco/utils.py
ddtrace_graphql_juaco-0.3.2.dist-info/licenses/LICENSE
ddtrace_graphql_juaco-0.3.2.dist-info/METADATA
ddtrace_graphql_juaco-0.3.2.dist-info/WHEEL
ddtrace_graphql_juaco-0.3.2.dist-info/top_level.txt
ddtrace_graphql_juaco-0.3.2.dist-info/RECORD
