Metadata-Version: 2.4
Name: ddtrace-graphql-juaco
Version: 0.3.2
Summary: Python library for tracing graphql calls with Datadog
Home-page: https://github.com/vamolin/ddtrace-graphql
Author: Michal Kuffa
Author-email: michal@bynder.com
License: MIT
Keywords: tracing datadog graphql graphene
Classifier: Intended Audience :: Developers
Classifier: Topic :: Software Development :: Debuggers
Classifier: License :: OSI Approved :: MIT License
Classifier: Programming Language :: Python :: 3
Classifier: Programming Language :: Python :: 3.5
Classifier: Programming Language :: Python :: 3.6
License-File: LICENSE
Requires-Dist: ddtrace
Requires-Dist: graphql-core
Requires-Dist: wrapt
Provides-Extra: test
Requires-Dist: tox; extra == "test"
Requires-Dist: pytest; extra == "test"
Requires-Dist: pytest-cov; extra == "test"
Dynamic: author
Dynamic: author-email
Dynamic: classifier
Dynamic: description
Dynamic: description-content-type
Dynamic: home-page
Dynamic: keywords
Dynamic: license
Dynamic: license-file
Dynamic: provides-extra
Dynamic: requires-dist
Dynamic: summary
